{
    "data": {
        "questions": [
            {
                "text": "<p>Consider a sphere of radius R which carries a uniform charge density ρ. If a sphere of radius&nbsp;\n <math xmlns=\"http://www.w3.org/1998/Math/MathML\">\n  <mfrac>\n   <mi mathvariant=\"normal\">\n    R\n   </mi>\n   <mn>\n    2\n   </mn>\n  </mfrac>\n </math>&nbsp;is carved out of it, as shown, the ratio&nbsp;\n <math xmlns=\"http://www.w3.org/1998/Math/MathML\">\n  <mfrac>\n   <mrow>\n    <mo>\n     |\n    </mo>\n    <msub>\n     <mover>\n      <mi mathvariant=\"normal\">\n       E\n      </mi>\n      <mo>\n       →\n      </mo>\n     </mover>\n     <mtext>\n      A\n     </mtext>\n    </msub>\n    <mo>\n     |\n    </mo>\n   </mrow>\n   <mrow>\n    <mo>\n     |\n    </mo>\n    <msub>\n     <mover>\n      <mi mathvariant=\"normal\">\n       E\n      </mi>\n      <mo>\n       →\n      </mo>\n     </mover>\n     <mtext>\n      B\n     </mtext>\n    </msub>\n    <mo>\n     |\n    </mo>\n   </mrow>\n  </mfrac>\n </math>&nbsp;of magnitude of electric field&nbsp;\n <math xmlns=\"http://www.w3.org/1998/Math/MathML\">\n  <msub>\n   <mover accent=\"true\">\n    <mi mathvariant=\"normal\">\n     E\n    </mi>\n    <mo>\n     →\n    </mo>\n   </mover>\n   <mi mathvariant=\"normal\">\n    A\n   </mi>\n  </msub>\n </math>&nbsp;and&nbsp;\n <math xmlns=\"http://www.w3.org/1998/Math/MathML\">\n  <msub>\n   <mover accent=\"true\">\n    <mi mathvariant=\"normal\">\n     E\n    </mi>\n    <mo>\n     →\n    </mo>\n   </mover>\n   <mi mathvariant=\"normal\">\n    B\n   </mi>\n  </msub>\n </math>, respectively, at points A and B due to the remaining portion is:&nbsp;</p>\n<figure class=\"image\">\n <img src=\"https://d29zr2abydv3bb.cloudfront.net/lcmsnode/QuestionImages/1622613297376image.png\">\n</figure>",
                "choices": [
                    {
                        "text": "<math>\n <mrow>\n  <mfrac>\n   <mrow>\n    <mn>\n     18\n    </mn>\n   </mrow>\n   <mrow>\n    <mn>\n     34\n    </mn>\n   </mrow>\n  </mfrac>\n </mrow>\n</math>",
                        "choiceId": "A",
                        "is_answer": true,
                        "explanation": ""
                    },
                    {
                        "text": "<math>\n <mrow>\n  <mfrac>\n   <mrow>\n    <mn>\n     18\n    </mn>\n   </mrow>\n   <mrow>\n    <mn>\n     54\n    </mn>\n   </mrow>\n  </mfrac>\n </mrow>\n</math>",
                        "choiceId": "B",
                        "is_answer": false,
                        "explanation": ""
                    },
                    {
                        "text": "<math>\n <mrow>\n  <mfrac>\n   <mrow>\n    <mn>\n     21\n    </mn>\n   </mrow>\n   <mrow>\n    <mn>\n     34\n    </mn>\n   </mrow>\n  </mfrac>\n </mrow>\n</math>",
                        "choiceId": "C",
                        "is_answer": false,
                        "explanation": ""
                    },
                    {
                        "text": "<math>\n <mrow>\n  <mfrac>\n   <mrow>\n    <mn>\n     17\n    </mn>\n   </mrow>\n   <mrow>\n    <mn>\n     54\n    </mn>\n   </mrow>\n  </mfrac>\n </mrow>\n</math>",
                        "choiceId": "D",
                        "is_answer": false,
                        "explanation": ""
                    }
                ],
                "solution": "<img width=\"133\" height=\"122\" id=\"Picture 11\" src=\"https://d3vo8rtp78h2dc.cloudfront.net/lcmsnode/Image/1614875739645/JM20Phyimage016.png\">\n<br> \n<math>\n <mrow>\n  <msub>\n   <mi>\n    E\n   </mi>\n   <mi>\n    A\n   </mi>\n  </msub>\n  <mo>\n   =\n  </mo>\n  <mfrac>\n   <mrow>\n    <mi>\n     σ\n    </mi>\n    <mo stretchy=\"false\">\n     (\n    </mo>\n    <mi>\n     R\n    </mi>\n    <mo>\n     /\n    </mo>\n    <mn>\n     2\n    </mn>\n    <mo stretchy=\"false\">\n     )\n    </mo>\n   </mrow>\n   <mrow>\n    <mn>\n     3\n    </mn>\n    <msub>\n     <mi>\n      ε\n     </mi>\n     <mn>\n      0\n     </mn>\n    </msub>\n   </mrow>\n  </mfrac>\n  <mo>\n   =\n  </mo>\n  <mfenced>\n   <mrow>\n    <mfrac>\n     <mrow>\n      <mi>\n       σ\n      </mi>\n      <mi>\n       R\n      </mi>\n     </mrow>\n     <mrow>\n      <mn>\n       6\n      </mn>\n      <msub>\n       <mi>\n        ε\n       </mi>\n       <mn>\n        0\n       </mn>\n      </msub>\n     </mrow>\n    </mfrac>\n   </mrow>\n  </mfenced>\n </mrow>\n</math>\n<br> \n<math>\n <mrow>\n  <msub>\n   <mi>\n    E\n   </mi>\n   <mi>\n    B\n   </mi>\n  </msub>\n  <mo>\n   =\n  </mo>\n  <mfrac>\n   <mrow>\n    <mi>\n     σ\n    </mi>\n    <mi>\n     R\n    </mi>\n   </mrow>\n   <mrow>\n    <mn>\n     3\n    </mn>\n    <msub>\n     <mi>\n      ε\n     </mi>\n     <mn>\n      0\n     </mn>\n    </msub>\n   </mrow>\n  </mfrac>\n  <mo>\n   –\n  </mo>\n  <mfenced>\n   <mrow>\n    <mfrac>\n     <mn>\n      1\n     </mn>\n     <mrow>\n      <mn>\n       4\n      </mn>\n      <mi>\n       π\n      </mi>\n      <msub>\n       <mi>\n        ε\n       </mi>\n       <mn>\n        0\n       </mn>\n      </msub>\n     </mrow>\n    </mfrac>\n   </mrow>\n  </mfenced>\n  <mfrac>\n   <mrow>\n    <mo stretchy=\"false\">\n     (\n    </mo>\n    <mi>\n     σ\n    </mi>\n    <mo stretchy=\"false\">\n     )\n    </mo>\n   </mrow>\n   <mrow>\n    <msup>\n     <mrow>\n      <mfenced>\n       <mrow>\n        <mfrac>\n         <mrow>\n          <mn>\n           3\n          </mn>\n          <mi>\n           R\n          </mi>\n         </mrow>\n         <mn>\n          2\n         </mn>\n        </mfrac>\n       </mrow>\n      </mfenced>\n     </mrow>\n     <mn>\n      2\n     </mn>\n    </msup>\n   </mrow>\n  </mfrac>\n  <mfrac>\n   <mrow>\n    <mn>\n     4\n    </mn>\n    <mi>\n     π\n    </mi>\n   </mrow>\n   <mn>\n    3\n   </mn>\n  </mfrac>\n  <msup>\n   <mrow>\n    <mfenced>\n     <mrow>\n      <mfrac>\n       <mi>\n        R\n       </mi>\n       <mn>\n        2\n       </mn>\n      </mfrac>\n     </mrow>\n    </mfenced>\n   </mrow>\n   <mn>\n    3\n   </mn>\n  </msup>\n </mrow>\n</math>\n<br> \n<math>\n <mrow>\n  <mo>\n   =\n  </mo>\n  <mfrac>\n   <mrow>\n    <mi>\n     σ\n    </mi>\n    <mi>\n     R\n    </mi>\n   </mrow>\n   <mrow>\n    <mn>\n     3\n    </mn>\n    <msub>\n     <mi>\n      ε\n     </mi>\n     <mn>\n      0\n     </mn>\n    </msub>\n   </mrow>\n  </mfrac>\n  <mo>\n   –\n  </mo>\n  <mfrac>\n   <mrow>\n    <mi>\n     σ\n    </mi>\n    <mi>\n     R\n    </mi>\n   </mrow>\n   <mrow>\n    <mn>\n     54\n    </mn>\n    <msub>\n     <mi>\n      ε\n     </mi>\n     <mn>\n      0\n     </mn>\n    </msub>\n   </mrow>\n  </mfrac>\n </mrow>\n</math>\n<br> \n<math>\n <mrow>\n  <mo>\n   ⇒\n  </mo>\n  <mtext>\n    \n  </mtext>\n  <mtext>\n    \n  </mtext>\n  <mtext>\n    \n  </mtext>\n  <msub>\n   <mi>\n    E\n   </mi>\n   <mi>\n    B\n   </mi>\n  </msub>\n  <mo>\n   =\n  </mo>\n  <mfrac>\n   <mrow>\n    <mn>\n     17\n    </mn>\n   </mrow>\n   <mrow>\n    <mn>\n     54\n    </mn>\n   </mrow>\n  </mfrac>\n  <mfenced>\n   <mrow>\n    <mfrac>\n     <mrow>\n      <mi>\n       σ\n      </mi>\n      <mi>\n       R\n      </mi>\n     </mrow>\n     <mrow>\n      <msub>\n       <mi>\n        ε\n       </mi>\n       <mn>\n        0\n       </mn>\n      </msub>\n     </mrow>\n    </mfrac>\n   </mrow>\n  </mfenced>\n </mrow>\n</math>\n<br> \n<math>\n <mrow>\n  <mfenced close=\"|\" open=\"|\">\n   <mrow>\n    <mfrac>\n     <mrow>\n      <msub>\n       <mi>\n        E\n       </mi>\n       <mi>\n        A\n       </mi>\n      </msub>\n     </mrow>\n     <mrow>\n      <msub>\n       <mi>\n        E\n       </mi>\n       <mi>\n        B\n       </mi>\n      </msub>\n     </mrow>\n    </mfrac>\n   </mrow>\n  </mfenced>\n  <mo>\n   =\n  </mo>\n  <mfrac>\n   <mrow>\n    <mn>\n     1\n    </mn>\n    <mo>\n     ×\n    </mo>\n    <mn>\n     54\n    </mn>\n   </mrow>\n   <mrow>\n    <mn>\n     6\n    </mn>\n    <mo>\n     ×\n    </mo>\n    <mn>\n     17\n    </mn>\n   </mrow>\n  </mfrac>\n  <mo>\n   =\n  </mo>\n  <mfenced>\n   <mrow>\n    <mfrac>\n     <mn>\n      9\n     </mn>\n     <mrow>\n      <mn>\n       17\n      </mn>\n     </mrow>\n    </mfrac>\n   </mrow>\n  </mfenced>\n </mrow>\n</math>",
                "underlying_concept": "Electric Field",
                "new_possible_concepts": "· Gauss law is useful for calculation of electric field due to symmetric charge distribution.\n<br> · Principle of superposition can be used to calculate electric field due to a combination of various charge distributions."
            },
            {
                "text": "<p>An electric dipole of moment&nbsp;\n <math xmlns=\"http://www.w3.org/1998/Math/MathML\">\n  <mover accent=\"true\">\n   <mi>\n    p\n   </mi>\n   <mo>\n    →\n   </mo>\n  </mover><mo>\n   =\n  </mo><mrow>\n   <mo>\n    (\n   </mo>\n   <mo>\n    -\n   </mo>\n   <mover accent=\"true\">\n    <mi>\n     i\n    </mi>\n    <mo>\n     ^\n    </mo>\n   </mover>\n   <mo>\n    -\n   </mo>\n   <mn>\n    3\n   </mn>\n   <mover accent=\"true\">\n    <mi>\n     j\n    </mi>\n    <mo>\n     ^\n    </mo>\n   </mover>\n   <mo>\n    +\n   </mo>\n   <mn>\n    2\n   </mn>\n   <mover accent=\"true\">\n    <mi>\n     k\n    </mi>\n    <mo>\n     ^\n    </mo>\n   </mover>\n   <mo>\n    )\n   </mo>\n  </mrow><mo>\n   ×\n  </mo><msup>\n   <mn>\n    10\n   </mn>\n   <mrow>\n    <mo>\n     -\n    </mo>\n    <mn>\n     29\n    </mn>\n   </mrow>\n  </msup>\n </math>&nbsp;C.m is at the origin (0, 0, 0). The electric field due to this dipole at&nbsp;\n <math>\n  <mrow>\n   <mover accent=\"true\">\n    <mi>\n     r\n    </mi>&nbsp;\n    <mo>\n     →\n    </mo>&nbsp;&nbsp;\n   </mover>\n   <mo>\n    =\n   </mo>\n   <mo>\n    +\n   </mo>\n   <mover accent=\"true\">\n    &nbsp;\n    <mi>\n     i\n    </mi>&nbsp;\n    <mo>\n     ^\n    </mo>&nbsp;&nbsp;\n   </mover>\n   <mo>\n    +\n   </mo>\n   <mn>\n    3\n   </mn>\n   <mover accent=\"true\">\n    &nbsp;\n    <mi>\n     j\n    </mi>&nbsp;\n    <mo>\n     ^\n    </mo>&nbsp;&nbsp;\n   </mover>\n   <mo>\n    +\n   </mo>\n   <mn>\n    5\n   </mn>\n   <mover accent=\"true\">\n    &nbsp;\n    <mi>\n     k\n    </mi>&nbsp;\n    <mo>\n     ^\n    </mo>&nbsp;&nbsp;\n   </mover>\n  </mrow>\n </math>&nbsp;</p>\n<p>(note that&nbsp;\n <math xmlns=\"http://www.w3.org/1998/Math/MathML\">\n  <mover accent=\"true\">\n   <mi>\n    r\n   </mi>\n   <mo>\n    →\n   </mo>\n  </mover><mo>\n   .\n  </mo><mtext>\n    \n  </mtext><mover accent=\"true\">\n   <mi>\n    p\n   </mi>\n   <mo>\n    →\n   </mo>\n  </mover><mtext>\n   =0\n  </mtext>\n </math>) is <span style=\"background-color:rgb(255,255,255);color:rgb(0,0,0);\"><strong>parallel </strong></span>to</p>",
                "choices": [
                    {
                        "text": "<math>\n <mrow>\n  <mfenced>\n   <mrow>\n    <mo>\n     –\n    </mo>\n    <mover accent=\"true\">\n     <mi>\n      i\n     </mi>\n     <mo>\n      ^\n     </mo>\n    </mover>\n    <mo>\n     –\n    </mo>\n    <mn>\n     3\n    </mn>\n    <mover accent=\"true\">\n     <mi>\n      j\n     </mi>\n     <mo>\n      ^\n     </mo>\n    </mover>\n    <mo>\n     +\n    </mo>\n    <mn>\n     2\n    </mn>\n    <mover accent=\"true\">\n     <mi>\n      k\n     </mi>\n     <mo>\n      ^\n     </mo>\n    </mover>\n   </mrow>\n  </mfenced>\n </mrow>\n</math>",
                        "choiceId": "A",
                        "is_answer": false,
                        "explanation": ""
                    },
                    {
                        "text": "<math>\n <mrow>\n  <mfenced>\n   <mrow>\n    <mo>\n     +\n    </mo>\n    <mover accent=\"true\">\n     <mi>\n      i\n     </mi>\n     <mo>\n      ^\n     </mo>\n    </mover>\n    <mo>\n     –\n    </mo>\n    <mn>\n     3\n    </mn>\n    <mover accent=\"true\">\n     <mi>\n      j\n     </mi>\n     <mo>\n      ^\n     </mo>\n    </mover>\n    <mo>\n     –\n    </mo>\n    <mn>\n     2\n    </mn>\n    <mover accent=\"true\">\n     <mi>\n      k\n     </mi>\n     <mo>\n      ^\n     </mo>\n    </mover>\n   </mrow>\n  </mfenced>\n </mrow>\n</math>",
                        "choiceId": "B",
                        "is_answer": false,
                        "explanation": ""
                    },
                    {
                        "text": "<math>\n <mrow>\n  <mfenced>\n   <mrow>\n    <mo>\n     –\n    </mo>\n    <mover accent=\"true\">\n     <mi>\n      i\n     </mi>\n     <mo>\n      ^\n     </mo>\n    </mover>\n    <mo>\n     +\n    </mo>\n    <mn>\n     3\n    </mn>\n    <mover accent=\"true\">\n     <mi>\n      j\n     </mi>\n     <mo>\n      ^\n     </mo>\n    </mover>\n    <mo>\n     –\n    </mo>\n    <mn>\n     2\n    </mn>\n    <mover accent=\"true\">\n     <mi>\n      k\n     </mi>\n     <mo>\n      ^\n     </mo>\n    </mover>\n   </mrow>\n  </mfenced>\n </mrow>\n</math>",
                        "choiceId": "C",
                        "is_answer": false,
                        "explanation": ""
                    },
                    {
                        "text": "<math>\n <mrow>\n  <mfenced>\n   <mrow>\n    <mo>\n     +\n    </mo>\n    <mover accent=\"true\">\n     <mi>\n      i\n     </mi>\n     <mo>\n      ^\n     </mo>\n    </mover>\n    <mo>\n     +\n    </mo>\n    <mn>\n     3\n    </mn>\n    <mover accent=\"true\">\n     <mi>\n      j\n     </mi>\n     <mo>\n      ^\n     </mo>\n    </mover>\n    <mo>\n     –\n    </mo>\n    <mn>\n     2\n    </mn>\n    <mover accent=\"true\">\n     <mi>\n      k\n     </mi>\n     <mo>\n      ^\n     </mo>\n    </mover>\n   </mrow>\n  </mfenced>\n </mrow>\n</math>",
                        "choiceId": "D",
                        "is_answer": true,
                        "explanation": ""
                    }
                ],
                "solution": "<p>\n <math xmlns=\"http://www.w3.org/1998/Math/MathML\">\n  <mover accent=\"true\">\n   <mi>\n    E\n   </mi>\n   <mo>\n    ^\n   </mo>\n  </mover><mo>\n   =\n  </mo><mo>\n   &nbsp;\n  </mo><mo>\n   –\n  </mo><mover accent=\"true\">\n   <mi>\n    p\n   </mi>\n   <mo>\n    ^\n   </mo>\n  </mover>\n </math><br>⇒&nbsp;&nbsp;\n <math xmlns=\"http://www.w3.org/1998/Math/MathML\">\n  <mover accent=\"true\">\n   <mi>\n    E\n   </mi>\n   <mo>\n    ^\n   </mo>\n  </mover><mo>\n   =\n  </mo><mo>\n   &nbsp;\n  </mo><mo>\n   –\n  </mo><mfenced close=\"]\" open=\"[\">\n   <mfrac>\n    <mrow>\n     <mo>\n      –\n     </mo>\n     <mover accent=\"true\">\n      <mi>\n       i\n      </mi>\n      <mo>\n       ^\n      </mo>\n     </mover>\n     <mo>\n      –\n     </mo>\n     <mn>\n      3\n     </mn>\n     <mover accent=\"true\">\n      <mi>\n       j\n      </mi>\n      <mo>\n       ^\n      </mo>\n     </mover>\n     <mo>\n      +\n     </mo>\n     <mn>\n      2\n     </mn>\n     <mover accent=\"true\">\n      <mi>\n       k\n      </mi>\n      <mo>\n       ^\n      </mo>\n     </mover>\n    </mrow>\n    <msqrt>\n     <mn>\n      14\n     </mn>\n    </msqrt>\n   </mfrac>\n  </mfenced>\n </math></p>\n<figure class=\"image\">\n <img src=\"https://d29zr2abydv3bb.cloudfront.net/lcmsnode/QuestionImages/1622614952241image.png\">\n</figure>\n<p>\n <math>\n  <mrow>\n   <mo>\n    |\n   </mo>&nbsp;&nbsp;\n   <mover accent=\"true\">\n    <mi>\n     E\n    </mi>&nbsp;&nbsp;\n    <mo>\n     →\n    </mo>&nbsp;&nbsp;\n   </mover>\n   <mo>\n    |\n   </mo>&nbsp;&nbsp;\n   <mo>\n    =\n   </mo>&nbsp;&nbsp;\n   <mfrac>\n    <mrow>\n     <mi>\n      k\n     </mi>&nbsp;&nbsp;\n     <mo>\n      |\n     </mo>&nbsp;&nbsp;\n     <mover accent=\"true\">\n      <mi>\n       p\n      </mi>&nbsp;&nbsp;\n      <mo>\n       →\n      </mo>&nbsp;&nbsp;\n     </mover>\n     <mo>\n      |\n     </mo>&nbsp;&nbsp;\n    </mrow>\n    <mrow>\n     <msup>\n      <mi>\n       r\n      </mi>&nbsp;&nbsp;\n      <mn>\n       3\n      </mn>&nbsp;&nbsp;\n     </msup>\n    </mrow>\n   </mfrac>\n  </mrow>\n </math></p>\n<p>\n <math>\n  <mover accent=\"true\">\n   <mi>\n    E\n   </mi>&nbsp;&nbsp;\n   <mo>\n    ^\n   </mo>&nbsp;&nbsp;\n  </mover>\n </math>&nbsp;is parallel to&nbsp;&nbsp;\n <math>\n  <mrow>\n   <mfenced>\n    <mrow>\n     <mover accent=\"true\">\n      <mi>\n       i\n      </mi>&nbsp;&nbsp;\n      <mo>\n       ^\n      </mo>&nbsp;&nbsp;\n     </mover>\n     <mo>\n      +\n     </mo>&nbsp;&nbsp;\n     <mn>\n      3\n     </mn>&nbsp;&nbsp;\n     <mover accent=\"true\">\n      <mi>\n       j\n      </mi>&nbsp;&nbsp;\n      <mo>\n       ^\n      </mo>&nbsp;&nbsp;\n     </mover>\n     <mo>\n      –\n     </mo>&nbsp;&nbsp;\n     <mn>\n      2\n     </mn>&nbsp;&nbsp;\n     <mover accent=\"true\">\n      <mi>\n       k\n      </mi>&nbsp;&nbsp;\n      <mo>\n       ^\n      </mo>&nbsp;&nbsp;\n     </mover>\n    </mrow>\n   </mfenced>\n  </mrow>\n </math></p>"
            },
            {
                "text": "<p style=\"text-align:justify;\">An electric field&nbsp;&nbsp;&nbsp;\n <math>\n  <mrow>\n   <mover accent=\"true\">\n    <mi>\n     E\n    </mi>&nbsp;&nbsp;&nbsp;\n    <mo>\n     →\n    </mo>&nbsp;&nbsp;&nbsp;&nbsp;\n   </mover>\n   <mo>\n    =\n   </mo>&nbsp;&nbsp;\n   <mn>\n    4\n   </mn>&nbsp;&nbsp;\n   <mi>\n    x\n   </mi>&nbsp;&nbsp;\n   <mover accent=\"true\">\n    &nbsp; &nbsp;\n    <mi>\n     i\n    </mi>&nbsp;&nbsp;&nbsp;\n    <mo stretchy=\"true\">\n     ^\n    </mo>&nbsp;&nbsp;&nbsp;&nbsp;\n   </mover>\n   <mo>\n    −\n   </mo>&nbsp;&nbsp;\n   <mrow>\n    <mo>\n     (\n    </mo>&nbsp;&nbsp;&nbsp;\n    <mrow>\n     <msup>\n      <mi>\n       y\n      </mi>&nbsp;&nbsp;&nbsp;\n      <mn>\n       2\n      </mn>&nbsp;&nbsp;&nbsp;&nbsp;\n     </msup>\n     <mo>\n      +\n     </mo>&nbsp;&nbsp;\n     <mn>\n      1\n     </mn>&nbsp;&nbsp;&nbsp;&nbsp;\n    </mrow>\n    <mo>\n     )\n    </mo>&nbsp;&nbsp;&nbsp;\n   </mrow>\n   <mover accent=\"true\">\n    &nbsp; &nbsp;\n    <mi>\n     j\n    </mi>&nbsp;&nbsp;&nbsp;\n    <mo stretchy=\"true\">\n     ^\n    </mo>&nbsp;&nbsp;&nbsp;&nbsp;\n   </mover>\n   <mtext>\n     \n   </mtext>\n   <mtext>\n     \n   </mtext>\n   <mtext>\n    N/C\n   </mtext>&nbsp;&nbsp;&nbsp;&nbsp;\n  </mrow>\n </math>&nbsp;passes through the box shown in figure. The flux of the electric field through surfaces ABCD and BCGF are marked as&nbsp;&nbsp;\n <math>\n  <msub>\n   <mi>\n    ϕ\n   </mi>&nbsp;&nbsp;\n   <mi>\n    I\n   </mi>&nbsp;&nbsp;&nbsp;\n  </msub>\n </math>&nbsp;and&nbsp;&nbsp;\n <math xmlns=\"http://www.w3.org/1998/Math/MathML\">\n  <msub>\n   <mi>\n    ϕ\n   </mi>&nbsp;\n   <mrow>\n    <mi>\n     I\n    </mi>&nbsp;\n    <mi>\n     I\n    </mi>&nbsp;&nbsp;\n   </mrow>\n  </msub>\n </math>&nbsp;respectively. The difference between&nbsp;\n <math>\n  <mrow>\n   <mo>\n    (\n   </mo>&nbsp;\n   <mrow>\n    <msub>\n     <mi>\n      ϕ\n     </mi>&nbsp;\n     <mi>\n      I\n     </mi>&nbsp;&nbsp;\n    </msub>\n    <mo>\n     −\n    </mo>\n    <msub>\n     &nbsp;\n     <mi>\n      ϕ\n     </mi>&nbsp;\n     <mrow>\n      <mi>\n       I\n      </mi>\n      <mi>\n       I\n      </mi>&nbsp;&nbsp;\n     </mrow>\n    </msub>\n   </mrow>\n   <mo>\n    )\n   </mo>&nbsp;\n  </mrow>&nbsp;&nbsp;\n </math>&nbsp;is (in Nm<sup>2</sup>/C) ______.</p>\n<figure class=\"image\">\n <img src=\"https://d3vo8rtp78h2dc.cloudfront.net/lcmsnode/QuestionImages/1622696985839image.png\">\n</figure>",
                "solution": "<p> \n <math> <msub> \n   <mi>\n    ϕ\n   </mi> \n   <mi>\n    I\n   </mi> \n  </msub> <mo>\n   =\n  </mo> <mo>\n   ∫\n  </mo> <mover accent=\"true\"> \n   <mi>\n    E\n   </mi> \n   <mo>\n    →\n   </mo> \n  </mover> <mo>\n   .\n  </mo> <mover accent=\"true\"> \n   <mrow> \n    <mi>\n     d\n    </mi> \n    <mi>\n     A\n    </mi> \n   </mrow> \n   <mo>\n    →\n   </mo> \n  </mover> <mo>\n   =\n  </mo> <mn>\n   0\n  </mn> \n </math> <br> \n <math> <msub> \n   <mi>\n    ϕ\n   </mi>&nbsp; \n   <mrow> \n    <mi>\n     I\n    </mi> \n    <mi>\n     I\n    </mi>&nbsp; \n   </mrow> \n  </msub> <mo>\n   =\n  </mo> <mrow> \n   <mo>\n    [\n   </mo>&nbsp; \n   <mrow> \n    <mn>\n     4\n    </mn> \n    <mi>\n     x\n    </mi> \n    <mover accent=\"true\">\n     &nbsp; \n     <mi>\n      i\n     </mi>&nbsp; \n     <mo stretchy=\"true\">\n      ^\n     </mo>&nbsp; \n    </mover> \n    <mo>\n     −\n    </mo> \n    <mrow> \n     <mo>\n      (\n     </mo>&nbsp; \n     <mrow> \n      <msup> \n       <mi>\n        y\n       </mi>&nbsp; \n       <mn>\n        2\n       </mn>&nbsp; \n      </msup> \n      <mo>\n       +\n      </mo> \n      <mn>\n       1\n      </mn>&nbsp; \n     </mrow> \n     <mo>\n      )\n     </mo> \n    </mrow> \n    <mover accent=\"true\">\n     &nbsp; \n     <mi>\n      j\n     </mi>&nbsp; \n     <mo stretchy=\"true\">\n      ^\n     </mo>&nbsp; \n    </mover> \n   </mrow> \n   <mo>\n    ]\n   </mo> \n  </mrow> <mn>\n   .4\n  </mn> <mover accent=\"true\">\n   &nbsp; \n   <mi>\n    i\n   </mi>&nbsp; \n   <mo stretchy=\"true\">\n    ^\n   </mo>&nbsp; \n  </mover> \n </math> <br> \n <math> <mtext>\n    \n  </mtext> <mtext>\n    \n  </mtext> <mtext>\n    \n  </mtext> <mtext>\n    \n  </mtext> <mtext>\n    \n  </mtext> <mtext>\n    \n  </mtext> <mo>\n   =\n  </mo> <mn>\n   16\n  </mn> <mi>\n   x\n  </mi>&nbsp; \n </math> <br> \n <math> <msub> \n   <mi>\n    ϕ\n   </mi>&nbsp; \n   <mrow> \n    <mi>\n     I\n    </mi> \n    <mi>\n     I\n    </mi>&nbsp; \n   </mrow> \n  </msub> <mo>\n   =\n  </mo> <mfrac>\n   &nbsp; \n   <mrow> \n    <mn>\n     48\n    </mn> \n    <mi>\n     N\n    </mi> \n    <msup>\n     &nbsp; \n     <mi>\n      m\n     </mi>&nbsp; \n     <mn>\n      2\n     </mn>&nbsp; \n    </msup> \n   </mrow> \n   <mi>\n    C\n   </mi>&nbsp; \n  </mfrac> \n </math> <br> \n <math> <msub> \n   <mi>\n    ϕ\n   </mi>&nbsp; \n   <mi>\n    I\n   </mi>&nbsp; \n  </msub> <mo>\n   −\n  </mo> <msub>\n   &nbsp; \n   <mi>\n    ϕ\n   </mi>&nbsp; \n   <mrow> \n    <mi>\n     I\n    </mi> \n    <mi>\n     I\n    </mi>&nbsp; \n   </mrow> \n  </msub> <mo>\n   =\n  </mo> <mo>\n   −\n  </mo> <mn>\n   48\n  </mn>&nbsp; \n </math> </p>",
                "underlying_concept": "Electric flux",
                "new_possible_concepts": "<ul>\n <li>Physically electric flux represents the number of field lines passing through a given area.&nbsp;</li>\n <li>&nbsp;\n  <math>\n   <mi>\n    ϕ\n   </mi><mo>\n    =\n   </mo><mstyle displaystyle=\"true\">\n    &nbsp;\n    <mrow>\n     <msubsup>\n      <mo>\n       ∫\n      </mo>&nbsp;\n      <mrow>\n       &nbsp;\n      </mrow>\n      <mrow>\n       &nbsp;\n      </mrow>\n     </msubsup>\n     <mrow>\n      <mover accent=\"true\">\n       <mi>\n        E\n       </mi>&nbsp;\n       <mo>\n        →\n       </mo>&nbsp;\n      </mover>\n      <mo>\n       −\n      </mo>\n      <mover accent=\"true\">\n       &nbsp;\n       <mrow>\n        <mi>\n         d\n        </mi>\n        <mi>\n         s\n        </mi>&nbsp;\n       </mrow>\n       <mo stretchy=\"true\">\n        →\n       </mo>&nbsp;\n      </mover>\n     </mrow>\n    </mrow>\n   </mstyle>\n  </math></li>\n</ul>"
            },
            {
                "text": "Three charged particles A, B and C with charges –4q, 2q and –2q are present on the circumference of a circle of radius d. The charged particles A, C and centre O of the circle formed an equilateral triangle as shown in figure. Electric field at O along x-direction is\n<br> \n<img width=\"137\" height=\"138\" id=\"Picture 32\" src=\"https://d3vo8rtp78h2dc.cloudfront.net/lcmsnode/Image/1614875739655/JM20Phyimage076.png\">",
                "choices": [
                    {
                        "text": "<math>\n <mrow>\n  <mfrac>\n   <mrow>\n    <msqrt>\n     <mn>\n      3\n     </mn>\n    </msqrt>\n    <mi>\n     q\n    </mi>\n   </mrow>\n   <mrow>\n    <mi>\n     π\n    </mi>\n    <msub>\n     <mi>\n      ε\n     </mi>\n     <mn>\n      0\n     </mn>\n    </msub>\n    <msup>\n     <mi>\n      d\n     </mi>\n     <mn>\n      2\n     </mn>\n    </msup>\n   </mrow>\n  </mfrac>\n </mrow>\n</math>",
                        "choiceId": "A",
                        "is_answer": true,
                        "explanation": ""
                    },
                    {
                        "text": "<math>\n <mrow>\n  <mfrac>\n   <mrow>\n    <mn>\n     3\n    </mn>\n    <msqrt>\n     <mn>\n      3\n     </mn>\n    </msqrt>\n    <mi>\n     q\n    </mi>\n   </mrow>\n   <mrow>\n    <mn>\n     4\n    </mn>\n    <mi>\n     π\n    </mi>\n    <msub>\n     <mi>\n      ε\n     </mi>\n     <mn>\n      0\n     </mn>\n    </msub>\n    <msup>\n     <mi>\n      d\n     </mi>\n     <mn>\n      2\n     </mn>\n    </msup>\n   </mrow>\n  </mfrac>\n </mrow>\n</math>",
                        "choiceId": "B",
                        "is_answer": false,
                        "explanation": ""
                    },
                    {
                        "text": "<math>\n <mrow>\n  <mfrac>\n   <mrow>\n    <msqrt>\n     <mn>\n      3\n     </mn>\n    </msqrt>\n    <mi>\n     q\n    </mi>\n   </mrow>\n   <mrow>\n    <mn>\n     4\n    </mn>\n    <mi>\n     π\n    </mi>\n    <msub>\n     <mi>\n      ε\n     </mi>\n     <mn>\n      0\n     </mn>\n    </msub>\n    <msup>\n     <mi>\n      d\n     </mi>\n     <mn>\n      2\n     </mn>\n    </msup>\n   </mrow>\n  </mfrac>\n </mrow>\n</math>",
                        "choiceId": "C",
                        "is_answer": false,
                        "explanation": ""
                    },
                    {
                        "text": "<math>\n <mrow>\n  <mfrac>\n   <mrow>\n    <mn>\n     2\n    </mn>\n    <msqrt>\n     <mn>\n      3\n     </mn>\n    </msqrt>\n    <mi>\n     q\n    </mi>\n   </mrow>\n   <mrow>\n    <mi>\n     π\n    </mi>\n    <msub>\n     <mi>\n      ε\n     </mi>\n     <mn>\n      0\n     </mn>\n    </msub>\n    <msup>\n     <mi>\n      d\n     </mi>\n     <mn>\n      2\n     </mn>\n    </msup>\n   </mrow>\n  </mfrac>\n </mrow>\n</math>",
                        "choiceId": "D",
                        "is_answer": false,
                        "explanation": ""
                    }
                ],
                "solution": "<figure> \n <img src=\"https://d3vo8rtp78h2dc.cloudfront.net/lcmsnode/QuestionImages/1622620710996image.png\"> \n</figure> \n<p>Electric field due to charge +2q at centre O –&nbsp;&nbsp;</p> \n<p> \n <math xmlns=\"http://www.w3.org/1998/Math/MathML\"> <msub> \n   <mover accent=\"true\"> \n    <mi>\n     E\n    </mi>&nbsp; \n    <mo>\n     →\n    </mo>&nbsp; \n   </mover> \n   <mn>\n    1\n   </mn>&nbsp; \n  </msub> <mo>\n   =\n  </mo>&nbsp; <mfrac> \n   <mn>\n    1\n   </mn>&nbsp; \n   <mrow> \n    <mn>\n     4\n    </mn>&nbsp; \n    <mi>\n     π\n    </mi>&nbsp; \n    <msub> \n     <mi>\n      ε\n     </mi>&nbsp; \n     <mn>\n      0\n     </mn>&nbsp; \n    </msub> \n   </mrow> \n  </mfrac> <mfrac> \n   <mrow> \n    <mn>\n     2\n    </mn>&nbsp; \n    <mi>\n     q\n    </mi>&nbsp; \n   </mrow> \n   <msup> \n    <mi>\n     d\n    </mi>&nbsp; \n    <mn>\n     2\n    </mn>&nbsp; \n   </msup> \n  </mfrac> <mfenced close=\"]\" open=\"[\"> \n   <mfrac> \n    <mrow> \n     <mo>\n      +\n     </mo>&nbsp; \n     <msqrt> \n      <mn>\n       3\n      </mn>&nbsp; \n     </msqrt> \n     <mover accent=\"true\"> \n      <mi>\n       i\n      </mi>&nbsp; \n      <mo>\n       ^\n      </mo>&nbsp; \n     </mover> \n     <mo>\n      −\n     </mo>&nbsp; \n     <mover accent=\"true\"> \n      <mi>\n       j\n      </mi>&nbsp; \n      <mo>\n       ^\n      </mo>&nbsp; \n     </mover> \n    </mrow> \n    <mn>\n     2\n    </mn>&nbsp; \n   </mfrac> \n  </mfenced> \n </math> <br>Due to –2q&nbsp;&nbsp; </p> \n<p> \n <math class=\"wrs_chemistry\" xmlns=\"http://www.w3.org/1998/Math/MathML\"> <msub> \n   <mover accent=\"true\"> \n    <mi>\n     E\n    </mi>&nbsp; \n    <mo>\n     →\n    </mo>&nbsp; \n   </mover> \n   <mn>\n    2\n   </mn>&nbsp; \n  </msub> <mo>\n   =\n  </mo>&nbsp; <mfrac> \n   <mn>\n    1\n   </mn>&nbsp; \n   <mrow> \n    <mn>\n     4\n    </mn>&nbsp; \n    <mi>\n     π\n    </mi>&nbsp; \n    <msub> \n     <mi>\n      ε\n     </mi>&nbsp; \n     <mn>\n      0\n     </mn>&nbsp; \n    </msub> \n   </mrow> \n  </mfrac> <mo>\n   ×\n  </mo>&nbsp; <mfrac> \n   <mrow> \n    <mn>\n     2\n    </mn>&nbsp; \n    <mi>\n     q\n    </mi>&nbsp; \n   </mrow> \n   <msup> \n    <mi>\n     d\n    </mi>&nbsp; \n    <mn>\n     2\n    </mn>&nbsp; \n   </msup> \n  </mfrac> <mfenced close=\"]\" open=\"[\"> \n   <mfrac> \n    <mstyle displaystyle=\"true\"> \n     <msqrt> \n      <mn>\n       3\n      </mn>&nbsp; \n     </msqrt> \n     <mover accent=\"true\"> \n      <mi>\n       i\n      </mi>&nbsp; \n      <mo>\n       ^\n      </mo>&nbsp; \n     </mover> \n     <mo>\n      −\n     </mo>&nbsp; \n     <mover accent=\"true\"> \n      <mi>\n       j\n      </mi>&nbsp; \n      <mo>\n       ^\n      </mo>&nbsp; \n     </mover> \n    </mstyle> \n    <mstyle displaystyle=\"true\"> \n     <mn>\n      2\n     </mn>&nbsp; \n    </mstyle> \n   </mfrac> \n  </mfenced> \n </math> <br>Due to –4q&nbsp;&nbsp; </p> \n<p> \n <math class=\"wrs_chemistry\" xmlns=\"http://www.w3.org/1998/Math/MathML\"> <msub> \n   <mover accent=\"true\"> \n    <mi>\n     E\n    </mi>&nbsp; \n    <mo>\n     →\n    </mo>&nbsp; \n   </mover> \n   <mn>\n    2\n   </mn>&nbsp; \n  </msub> <mo>\n   =\n  </mo>&nbsp; <mfrac> \n   <mn>\n    1\n   </mn>&nbsp; \n   <mrow> \n    <mn>\n     4\n    </mn>&nbsp; \n    <mi>\n     π\n    </mi>&nbsp; \n    <msub> \n     <mi>\n      ε\n     </mi>&nbsp; \n     <mn>\n      0\n     </mn>&nbsp; \n    </msub> \n   </mrow> \n  </mfrac> <mo>\n   ×\n  </mo>&nbsp; <mfrac> \n   <mrow> \n    <mn>\n     2\n    </mn>&nbsp; \n    <mi>\n     q\n    </mi>&nbsp; \n   </mrow> \n   <msup> \n    <mi>\n     d\n    </mi>&nbsp; \n    <mn>\n     2\n    </mn>&nbsp; \n   </msup> \n  </mfrac> <mrow> \n   <mo>\n    [\n   </mo>&nbsp; \n   <mfrac> \n    <mrow> \n     <msqrt> \n      <mn>\n       3\n      </mn>&nbsp; \n     </msqrt> \n     <mover accent=\"true\"> \n      <mi>\n       i\n      </mi>&nbsp; \n      <mo>\n       ^\n      </mo>&nbsp; \n     </mover> \n     <mo>\n      −\n     </mo>&nbsp; \n     <mover accent=\"true\"> \n      <mi>\n       j\n      </mi>&nbsp; \n      <mo>\n       ^\n      </mo>&nbsp; \n     </mover> \n    </mrow> \n    <mn>\n     2\n    </mn>&nbsp; \n   </mfrac> \n   <mo>\n    ]\n   </mo>&nbsp; \n  </mrow> \n </math> <br>Net electric field at point O&nbsp; </p> \n<p> \n <math class=\"wrs_chemistry\" xmlns=\"http://www.w3.org/1998/Math/MathML\"> <msub> \n   <mover accent=\"true\"> \n    <mi>\n     E\n    </mi> \n    <mo>\n     →\n    </mo> \n   </mover> \n   <mn>\n    0\n   </mn> \n  </msub> <mo>\n   =\n  </mo> <msub> \n   <mover accent=\"true\"> \n    <mi>\n     E\n    </mi> \n    <mo>\n     →\n    </mo> \n   </mover> \n   <mn>\n    1\n   </mn> \n  </msub> <mo>\n   +\n  </mo> <msub> \n   <mover accent=\"true\"> \n    <mi>\n     E\n    </mi> \n    <mo>\n     →\n    </mo> \n   </mover> \n   <mn>\n    2\n   </mn> \n  </msub> <mo>\n   +\n  </mo> <msub> \n   <mover accent=\"true\"> \n    <mi>\n     E\n    </mi> \n    <mo>\n     →\n    </mo> \n   </mover> \n   <mn>\n    3\n   </mn> \n  </msub> <mo>\n   =\n  </mo> <mfrac> \n   <mrow> \n    <msqrt> \n     <mn>\n      3\n     </mn> \n    </msqrt> \n    <mi>\n     q\n    </mi> \n   </mrow> \n   <mrow> \n    <mi>\n     π\n    </mi> \n    <msub> \n     <mi>\n      ε\n     </mi> \n     <mn>\n      0\n     </mn> \n    </msub> \n    <msup> \n     <mi>\n      d\n     </mi> \n     <mn>\n      2\n     </mn> \n    </msup> \n   </mrow> \n  </mfrac> <mover accent=\"true\"> \n   <mi>\n    i\n   </mi> \n   <mo>\n    ^\n   </mo> \n  </mover> \n </math> </p>"
            },
            {
                "text": "<p>In finding the electric field using Gauss law the formula&nbsp;\n <math xmlns=\"http://www.w3.org/1998/Math/MathML\">\n  <mfenced close=\"|\" open=\"|\">\n   <mover accent=\"true\">\n    <mi>\n     E\n    </mi>\n    <mo>\n     →\n    </mo>\n   </mover>\n  </mfenced><mo>\n   =\n  </mo><mfrac>\n   <msub>\n    <mi>\n     q\n    </mi>\n    <mrow>\n     <mi>\n      e\n     </mi>\n     <mi>\n      n\n     </mi>\n     <mi>\n      c\n     </mi>\n    </mrow>\n   </msub>\n   <mrow>\n    <msub>\n     <mi>\n      ε\n     </mi>\n     <mn>\n      0\n     </mn>\n    </msub>\n    <mfenced close=\"|\" open=\"|\">\n     <mi>\n      A\n     </mi>\n    </mfenced>\n   </mrow>\n  </mfrac>\n </math>is applicable. In the formula ε<sub>0</sub> is permittivity of free space, A is the area of Gaussian surface and q<sub>enc</sub> is charge enclosed by the Gaussian surface. This equation can be used in which of the following situation?</p>",
                "choices": [
                    {
                        "text": "<p>Only when the Gaussian surface is an equipotential surface and&nbsp;\n <math>\n  <mrow>\n   <mfenced close=\"|\" open=\"|\">\n    <mrow>\n     <mover accent=\"true\">\n      <mi>\n       E\n      </mi>&nbsp;\n      <mo stretchy=\"true\">\n       →\n      </mo>&nbsp;\n     </mover>\n    </mrow>\n   </mfenced>\n  </mrow>\n </math>&nbsp;is constant on the surface.</p>",
                        "choiceId": "A",
                        "is_answer": true,
                        "explanation": ""
                    },
                    {
                        "text": "<p>Only when&nbsp;\n <math>\n  <mrow>\n   <mfenced close=\"|\" open=\"|\">\n    <mrow>\n     <mover accent=\"true\">\n      <mi>\n       E\n      </mi>&nbsp;\n      <mo stretchy=\"true\">\n       →\n      </mo>&nbsp;\n     </mover>\n    </mrow>\n   </mfenced>\n  </mrow>\n </math>&nbsp;= constant on the surface.</p>",
                        "choiceId": "B",
                        "is_answer": false,
                        "explanation": ""
                    },
                    {
                        "text": "Only when the Gaussian surface is an equipotential surface.",
                        "choiceId": "C",
                        "is_answer": false,
                        "explanation": ""
                    },
                    {
                        "text": "For any choice of Gaussian surface.",
                        "choiceId": "D",
                        "is_answer": false,
                        "explanation": ""
                    }
                ],
                "solution": "<p>By Gauss law&nbsp;</p>\n<p>\n <math class=\"wrs_chemistry\" xmlns=\"http://www.w3.org/1998/Math/MathML\">\n  <mo>\n   ∮\n  </mo><mover accent=\"true\">\n   <mi>\n    E\n   </mi>\n   <mo>\n    →\n   </mo>\n  </mover><mo>\n   ⋅\n  </mo><mover accent=\"true\">\n   <mrow>\n    <mi>\n     d\n    </mi>\n    <mi>\n     A\n    </mi>\n   </mrow>\n   <mo>\n    →\n   </mo>\n  </mover><mo>\n   =\n  </mo><mfrac>\n   <msub>\n    <mi>\n     Q\n    </mi>\n    <mrow>\n     <mi>\n      i\n     </mi>\n     <mi>\n      n\n     </mi>\n    </mrow>\n   </msub>\n   <msub>\n    <mi>\n     ε\n    </mi>\n    <mn>\n     0\n    </mn>\n   </msub>\n  </mfrac>\n </math><br>If&nbsp;\n <math class=\"wrs_chemistry\" xmlns=\"http://www.w3.org/1998/Math/MathML\">\n  <mrow>\n   <mo>\n    |\n   </mo>\n   <mover accent=\"true\">\n    <mi>\n     E\n    </mi>\n    <mo>\n     →\n    </mo>\n   </mover>\n   <mo>\n    |\n   </mo>\n  </mrow><mo>\n   =\n  </mo><mfrac>\n   <msub>\n    <mi>\n     Q\n    </mi>\n    <mrow>\n     <mi>\n      i\n     </mi>\n     <mi>\n      n\n     </mi>\n    </mrow>\n   </msub>\n   <mrow>\n    <mrow>\n     <mo>\n      |\n     </mo>\n     <mover accent=\"true\">\n      <mi>\n       A\n      </mi>\n      <mo>\n       →\n      </mo>\n     </mover>\n     <mo>\n      |\n     </mo>\n    </mrow>\n    <msub>\n     <mi>\n      ε\n     </mi>\n     <mn>\n      0\n     </mn>\n    </msub>\n   </mrow>\n  </mfrac>\n </math><br>or&nbsp;\n <math class=\"wrs_chemistry\" xmlns=\"http://www.w3.org/1998/Math/MathML\">\n  <mrow>\n   <mo>\n    |\n   </mo>\n   <mover accent=\"true\">\n    <mi>\n     E\n    </mi>\n    <mo>\n     →\n    </mo>\n   </mover>\n   <mo>\n    |\n   </mo>\n  </mrow><mrow>\n   <mo>\n    |\n   </mo>\n   <mover accent=\"true\">\n    <mi>\n     A\n    </mi>\n    <mo>\n     →\n    </mo>\n   </mover>\n   <mo>\n    |\n   </mo>\n  </mrow><mo>\n   =\n  </mo><mfrac>\n   <msub>\n    <mi>\n     Q\n    </mi>\n    <mrow>\n     <mi>\n      i\n     </mi>\n     <mi>\n      n\n     </mi>\n    </mrow>\n   </msub>\n   <msub>\n    <mi>\n     ε\n    </mi>\n    <mn>\n     0\n    </mn>\n   </msub>\n  </mfrac>\n </math><br>then&nbsp;\n <math>\n  <mrow>\n   <mover accent=\"true\">\n    <mi>\n     E\n    </mi>&nbsp;\n    <mo>\n     →\n    </mo>&nbsp;\n   </mover>\n   <mo>\n    |\n   </mo>&nbsp;\n   <mo>\n    |\n   </mo>&nbsp;\n   <mover accent=\"true\">\n    <mi>\n     A\n    </mi>&nbsp;\n    <mo>\n     →\n    </mo>&nbsp;\n   </mover>\n  </mrow>\n </math><br>∴ Surface is equipotential too.</p>"
            },
            {
                "text": "<p>A particle of mass m and charge q is released from rest in a uniform electric field. If there is no other force on the particle, the dependence of its speed v on the distance x travelled by it is correctly given by (graphs are schematic and not drawn to scale)&nbsp;</p>",
                "choices": [
                    {
                        "text": "<img width=\"130\" height=\"82\" id=\"Picture 80\" src=\"https://d3vo8rtp78h2dc.cloudfront.net/lcmsnode/Image/1614875739660/JM20Phyimage104.png\">",
                        "choiceId": "A",
                        "is_answer": false,
                        "explanation": ""
                    },
                    {
                        "text": "<img width=\"130\" height=\"74\" id=\"Picture 81\" src=\"https://d3vo8rtp78h2dc.cloudfront.net/lcmsnode/Image/1614875739660/JM20Phyimage105.png\">",
                        "choiceId": "B",
                        "is_answer": false,
                        "explanation": ""
                    },
                    {
                        "text": "<img width=\"130\" height=\"75\" id=\"Picture 82\" src=\"https://d3vo8rtp78h2dc.cloudfront.net/lcmsnode/Image/1614875739660/JM20Phyimage106.png\">",
                        "choiceId": "C",
                        "is_answer": false,
                        "explanation": ""
                    },
                    {
                        "text": "<img width=\"130\" height=\"75\" id=\"Picture 83\" src=\"https://d3vo8rtp78h2dc.cloudfront.net/lcmsnode/Image/1614875739660/JM20Phyimage107.png\">",
                        "choiceId": "D",
                        "is_answer": true,
                        "explanation": ""
                    }
                ],
                "solution": "<figure class=\"image\">\n <img src=\"https://d3vo8rtp78h2dc.cloudfront.net/lcmsnode/Image/1614875739661/JM20Phyimage108.png\">\n</figure>\n<p><br>\n <math>\n  <mrow>\n   <msup>\n    <mi>\n     v\n    </mi>\n    <mn>\n     2\n    </mn>&nbsp;&nbsp;\n   </msup>\n   <mo>\n    =\n   </mo>\n   <mfrac>\n    <mrow>\n     <mn>\n      2\n     </mn>\n     <mi>\n      q\n     </mi>\n     <mi>\n      E\n     </mi>&nbsp;&nbsp;\n    </mrow>\n    <mi>\n     m\n    </mi>&nbsp;&nbsp;\n   </mfrac>\n   <mtext>\n     \n   </mtext>\n   <mo>\n    ·\n   </mo>\n   <mtext>\n     \n   </mtext>\n   <mi>\n    x\n   </mi>&nbsp;&nbsp;\n  </mrow>\n </math></p>",
                "underlying_concept": "Motion of charge in electric field",
                "new_possible_concepts": "<p>· Force exerted by electric field on a charge particle is given by</p>\n<p>\n <math xmlns=\"http://www.w3.org/1998/Math/MathML\">\n  <mover accent=\"true\">\n   <mi>\n    F\n   </mi>\n   <mo>\n    →\n   </mo>\n  </mover><mo>\n   =\n  </mo><mi>\n   q\n  </mi><mover accent=\"true\">\n   <mi>\n    E\n   </mi>\n   <mo>\n    →\n   </mo>\n  </mover>\n </math></p>\n<p>· If a particle is released from rest in uniform force field, then it moves along straight line in the direction of force with uniform acceleration.<br>· Path of a charged particle in uniform Electric field can be straight line OR parabolic depending on angle between its velocity and Electric field.</p>"
            },
            {
                "text": "Two infinite planes each with uniform surface charge density +σ are kept in such a way that the angle between them is 30°. The electric field in the region shown between them is given by\n<br> \n<img width=\"283\" height=\"140\" id=\"Picture 106\" src=\"https://d3vo8rtp78h2dc.cloudfront.net/lcmsnode/Image/1614875739673/JM20Phyimage136.png\">",
                "choices": [
                    {
                        "text": "<p>\n <math xmlns=\"http://www.w3.org/1998/Math/MathML\">\n  <mfrac>\n   <mi>\n    σ\n   </mi>\n   <mrow>\n    <mn>\n     2\n    </mn>\n    <msub>\n     <mi>\n      ε\n     </mi>\n     <mn>\n      0\n     </mn>\n    </msub>\n   </mrow>\n  </mfrac><mfenced close=\"]\" open=\"[\">\n   <mrow>\n    <mrow>\n     <mo>\n      (\n     </mo>\n     <mn>\n      1\n     </mn>\n     <mo>\n      +\n     </mo>\n     <msqrt>\n      <mn>\n       3\n      </mn>\n     </msqrt>\n     <mo>\n      )\n     </mo>\n    </mrow>\n    <mover accent=\"true\">\n     <mi>\n      y\n     </mi>\n     <mo>\n      ^\n     </mo>\n    </mover>\n    <mo>\n     +\n    </mo>\n    <mfrac>\n     <mover accent=\"true\">\n      <mi>\n       x\n      </mi>\n      <mo>\n       ^\n      </mo>\n     </mover>\n     <mn>\n      2\n     </mn>\n    </mfrac>\n   </mrow>\n  </mfenced>\n </math></p>",
                        "choiceId": "A",
                        "is_answer": false,
                        "explanation": ""
                    },
                    {
                        "text": "<p>\n <math xmlns=\"http://www.w3.org/1998/Math/MathML\">\n  <mfrac>\n   <mi>\n    σ\n   </mi>\n   <mrow>\n    <mn>\n     2\n    </mn>\n    <msub>\n     <mi>\n      ε\n     </mi>\n     <mn>\n      0\n     </mn>\n    </msub>\n   </mrow>\n  </mfrac><mfenced close=\"]\" open=\"[\">\n   <mrow>\n    <mrow>\n     <mo>\n      (\n     </mo>\n     <mn>\n      1\n     </mn>\n     <mo>\n      +\n     </mo>\n     <msqrt>\n      <mn>\n       3\n      </mn>\n     </msqrt>\n     <mo>\n      )\n     </mo>\n    </mrow>\n    <mover accent=\"true\">\n     <mi>\n      y\n     </mi>\n     <mo>\n      ^\n     </mo>\n    </mover>\n    <mo>\n     −\n    </mo>\n    <mfrac>\n     <mover accent=\"true\">\n      <mi>\n       x\n      </mi>\n      <mo>\n       ^\n      </mo>\n     </mover>\n     <mn>\n      2\n     </mn>\n    </mfrac>\n   </mrow>\n  </mfenced>\n </math></p>",
                        "choiceId": "B",
                        "is_answer": false,
                        "explanation": ""
                    },
                    {
                        "text": "<p>\n <math xmlns=\"http://www.w3.org/1998/Math/MathML\">\n  <mfrac>\n   <mi>\n    σ\n   </mi>\n   <mrow>\n    <mn>\n     2\n    </mn>\n    <msub>\n     <mi>\n      ε\n     </mi>\n     <mn>\n      0\n     </mn>\n    </msub>\n   </mrow>\n  </mfrac><mfenced close=\"]\" open=\"[\">\n   <mrow>\n    <mfenced>\n     <mrow>\n      <mn>\n       1\n      </mn>\n      <mo>\n       –\n      </mo>\n      <mfrac>\n       <msqrt>\n        <mn>\n         3\n        </mn>\n       </msqrt>\n       <mn>\n        2\n       </mn>\n      </mfrac>\n     </mrow>\n    </mfenced>\n    <mo>\n     &nbsp;\n    </mo>\n    <mover accent=\"true\">\n     <mi>\n      y\n     </mi>\n     <mo>\n      ^\n     </mo>\n    </mover>\n    <mo>\n     −\n    </mo>\n    <mfrac>\n     <mover accent=\"true\">\n      <mi>\n       x\n      </mi>\n      <mo>\n       ^\n      </mo>\n     </mover>\n     <mn>\n      2\n     </mn>\n    </mfrac>\n   </mrow>\n  </mfenced>\n </math></p>",
                        "choiceId": "C",
                        "is_answer": true,
                        "explanation": ""
                    },
                    {
                        "text": "<p>\n <math xmlns=\"http://www.w3.org/1998/Math/MathML\">\n  <mfrac>\n   <mi>\n    σ\n   </mi>\n   <mrow>\n    <mn>\n     2\n    </mn>\n    <msub>\n     <mi>\n      ε\n     </mi>\n     <mn>\n      0\n     </mn>\n    </msub>\n   </mrow>\n  </mfrac><mfenced close=\"]\" open=\"[\">\n   <mrow>\n    <mfenced>\n     <mrow>\n      <mn>\n       1\n      </mn>\n      <mo>\n       +\n      </mo>\n      <mfrac>\n       <msqrt>\n        <mn>\n         3\n        </mn>\n       </msqrt>\n       <mn>\n        2\n       </mn>\n      </mfrac>\n     </mrow>\n    </mfenced>\n    <mo>\n     &nbsp;\n    </mo>\n    <mover accent=\"true\">\n     <mi>\n      y\n     </mi>\n     <mo>\n      ^\n     </mo>\n    </mover>\n    <mo>\n     +\n    </mo>\n    <mfrac>\n     <mover accent=\"true\">\n      <mi>\n       x\n      </mi>\n      <mo>\n       ^\n      </mo>\n     </mover>\n     <mn>\n      2\n     </mn>\n    </mfrac>\n   </mrow>\n  </mfenced>\n </math></p>",
                        "choiceId": "D",
                        "is_answer": false,
                        "explanation": ""
                    }
                ],
                "solution": "<figure class=\"image\">\n <img src=\"https://d3vo8rtp78h2dc.cloudfront.net/lcmsnode/Image/1614875739674/JM20Phyimage137.png\">\n</figure>\n<p><br>\n <math>\n  <mrow>\n   <mover accent=\"true\">\n    <mrow>\n     <msub>\n      <mi>\n       E\n      </mi>\n      <mn>\n       1\n      </mn>&nbsp;\n     </msub>\n    </mrow>\n    <mo stretchy=\"true\">\n     →\n    </mo>&nbsp;\n   </mover>\n   <mo>\n    =\n   </mo>\n   <mfrac>\n    <mi>\n     σ\n    </mi>\n    <mrow>\n     <mn>\n      2\n     </mn>\n     <msub>\n      <mi>\n       ε\n      </mi>\n      <mn>\n       0\n      </mn>&nbsp;\n     </msub>\n    </mrow>\n   </mfrac>\n   <mtext>\n     \n   </mtext>\n   <mover accent=\"true\">\n    <mi>\n     y\n    </mi>\n    <mo>\n     ^\n    </mo>&nbsp;\n   </mover>\n  </mrow>\n </math><br>\n <math>\n  <mrow>\n   <mover accent=\"true\">\n    <mrow>\n     <msub>\n      <mi>\n       E\n      </mi>\n      <mn>\n       2\n      </mn>&nbsp;\n     </msub>\n    </mrow>\n    <mo stretchy=\"true\">\n     →\n    </mo>&nbsp;\n   </mover>\n   <mo>\n    =\n   </mo>\n   <mfrac>\n    <mi>\n     σ\n    </mi>\n    <mrow>\n     <mn>\n      2\n     </mn>\n     <msub>\n      <mi>\n       ε\n      </mi>\n      <mn>\n       0\n      </mn>&nbsp;\n     </msub>\n    </mrow>\n   </mfrac>\n   <mo stretchy=\"false\">\n    (\n   </mo>\n   <mo>\n    –\n   </mo>\n   <mi>\n    cos\n   </mi>\n   <mn>\n    60\n   </mn>\n   <mo>\n    °\n   </mo>\n   <mtext>\n     \n   </mtext>\n   <mover accent=\"true\">\n    <mi>\n     x\n    </mi>\n    <mo>\n     ^\n    </mo>&nbsp;\n   </mover>\n   <mo>\n    –\n   </mo>\n   <mi>\n    sin\n   </mi>\n   <mn>\n    60\n   </mn>\n   <mo>\n    °\n   </mo>\n   <mover accent=\"true\">\n    <mi>\n     y\n    </mi>\n    <mo>\n     ^\n    </mo>&nbsp;\n   </mover>\n   <mo stretchy=\"false\">\n    )\n   </mo>&nbsp;\n  </mrow>\n </math><br>\n <math>\n  <mrow>\n   <mo>\n    =\n   </mo>\n   <mfrac>\n    <mi>\n     σ\n    </mi>\n    <mrow>\n     <mn>\n      2\n     </mn>\n     <msub>\n      <mi>\n       ε\n      </mi>\n      <mn>\n       0\n      </mn>&nbsp;\n     </msub>\n    </mrow>\n   </mfrac>\n   <mfenced>\n    <mrow>\n     <mo>\n      –\n     </mo>\n     <mfrac>\n      <mn>\n       1\n      </mn>\n      <mn>\n       2\n      </mn>&nbsp;\n     </mfrac>\n     <mover accent=\"true\">\n      <mi>\n       x\n      </mi>\n      <mo>\n       ^\n      </mo>&nbsp;\n     </mover>\n     <mo>\n      –\n     </mo>\n     <mfrac>\n      <mrow>\n       <msqrt>\n        <mn>\n         3\n        </mn>&nbsp;\n       </msqrt>\n      </mrow>\n      <mn>\n       2\n      </mn>&nbsp;\n     </mfrac>\n     <mover accent=\"true\">\n      <mi>\n       y\n      </mi>\n      <mo>\n       ^\n      </mo>&nbsp;\n     </mover>\n    </mrow>\n   </mfenced>\n  </mrow>\n </math><br>\n <math>\n  <mrow>\n   <mo>\n    ∴\n   </mo>\n   <mtext>\n     \n   </mtext>\n   <mtext>\n     \n   </mtext>\n   <mtext>\n     \n   </mtext>\n   <mover accent=\"true\">\n    <mrow>\n     <msub>\n      <mi>\n       E\n      </mi>\n      <mi>\n       P\n      </mi>&nbsp;\n     </msub>\n    </mrow>\n    <mo stretchy=\"true\">\n     →\n    </mo>&nbsp;\n   </mover>\n   <mo>\n    =\n   </mo>\n   <mover accent=\"true\">\n    <mrow>\n     <msub>\n      <mi>\n       E\n      </mi>\n      <mn>\n       1\n      </mn>&nbsp;\n     </msub>\n    </mrow>\n    <mo stretchy=\"true\">\n     →\n    </mo>&nbsp;\n   </mover>\n   <mo>\n    +\n   </mo>\n   <mover accent=\"true\">\n    <mrow>\n     <msub>\n      <mi>\n       E\n      </mi>\n      <mn>\n       2\n      </mn>&nbsp;\n     </msub>\n    </mrow>\n    <mo stretchy=\"true\">\n     →\n    </mo>&nbsp;\n   </mover>\n   <mo>\n    =\n   </mo>\n   <mfrac>\n    <mi>\n     σ\n    </mi>\n    <mrow>\n     <mn>\n      2\n     </mn>\n     <msub>\n      <mi>\n       ε\n      </mi>\n      <mn>\n       0\n      </mn>&nbsp;\n     </msub>\n    </mrow>\n   </mfrac>\n   <mfenced close=\"]\" open=\"[\">\n    <mrow>\n     <mo>\n      –\n     </mo>\n     <mfrac>\n      <mn>\n       1\n      </mn>\n      <mn>\n       2\n      </mn>&nbsp;\n     </mfrac>\n     <mover accent=\"true\">\n      <mi>\n       x\n      </mi>\n      <mo>\n       ^\n      </mo>&nbsp;\n     </mover>\n     <mo>\n      +\n     </mo>\n     <mfenced>\n      <mrow>\n       <mn>\n        1\n       </mn>\n       <mo>\n        –\n       </mo>\n       <mfrac>\n        <mrow>\n         <msqrt>\n          <mn>\n           3\n          </mn>&nbsp;\n         </msqrt>\n        </mrow>\n        <mn>\n         2\n        </mn>&nbsp;\n       </mfrac>\n      </mrow>\n     </mfenced>\n     <mover accent=\"true\">\n      <mi>\n       y\n      </mi>\n      <mo>\n       ^\n      </mo>&nbsp;\n     </mover>\n    </mrow>\n   </mfenced>\n  </mrow>\n </math></p>",
                "underlying_concept": "Electric field due to infinite plane of charge",
                "new_possible_concepts": "<p>· For calculation of electric field due symmetric charge distribution, gauss law is a useful tool.&nbsp;<br>· According to gauss law, flux linked with a closed surface is given by&nbsp;\n <math>\n  <mi>\n   ϕ\n  </mi>&nbsp;&nbsp;&nbsp;\n </math>\n <math xmlns=\"http://www.w3.org/1998/Math/MathML\">\n  <mo>\n   =\n  </mo><mo>\n   ∮\n  </mo><mover accent=\"true\">\n   <mi>\n    E\n   </mi>\n   <mo>\n    →\n   </mo>\n  </mover><mo>\n   ⋅\n  </mo><mover accent=\"true\">\n   <mrow>\n    <mi>\n     d\n    </mi>\n    <mi>\n     s\n    </mi>\n   </mrow>\n   <mo>\n    →\n   </mo>\n  </mover><mo>\n   =\n  </mo><mfrac>\n   <mn>\n    1\n   </mn>\n   <msub>\n    <mi>\n     ε\n    </mi>\n    <mn>\n     0\n    </mn>\n   </msub>\n  </mfrac><msub>\n   <mi>\n    Q\n   </mi>\n   <mtext>\n    enc\n   </mtext>\n  </msub>\n </math></p>\n<figure class=\"image\">\n <img src=\"https://d3vo8rtp78h2dc.cloudfront.net/lcmsnode/Image/1614875739675/JM20Phyimage138.png\">\n</figure>",
                "type": "SCMCQ",
                "sub_type": null,
                "difficulty": "H",
                "year": [
                    2020
                ],
                "similar_question": [],
                "answer": null,
                "list1": null,
                "list2": null,
                "topic_id": null
            },
            {
                "chapter": {
                    "id": "94402",
                    "name": "Electric Charges and Fields"
                },
                "id": 6228,
                "text": "Charges Q<sub>1</sub> and Q<sub>2</sub> are at points A and B of a right angle triangle OAB (see figure). The resultant electric field at point O is perpendicular to the hypotenuse, then Q<sub>1</sub>/Q<sub>2</sub> is proportional to\n<br> \n<img width=\"148\" height=\"146\" id=\"Picture 132\" src=\"https://d3vo8rtp78h2dc.cloudfront.net/lcmsnode/Image/1614875739679/JM20Phyimage169.png\">",
                "choices": [
                    {
                        "text": "<math>\n <mrow>\n  <mfrac>\n   <mrow>\n    <msubsup>\n     <mi>\n      x\n     </mi>\n     <mn>\n      1\n     </mn>\n     <mn>\n      3\n     </mn>\n    </msubsup>\n   </mrow>\n   <mrow>\n    <msubsup>\n     <mi>\n      x\n     </mi>\n     <mn>\n      2\n     </mn>\n     <mn>\n      3\n     </mn>\n    </msubsup>\n   </mrow>\n  </mfrac>\n </mrow>\n</math>",
                        "choiceId": "A",
                        "is_answer": false,
                        "explanation": ""
                    },
                    {
                        "text": "<math>\n <mrow>\n  <mfrac>\n   <mrow>\n    <msubsup>\n     <mi>\n      x\n     </mi>\n     <mn>\n      2\n     </mn>\n     <mn>\n      2\n     </mn>\n    </msubsup>\n   </mrow>\n   <mrow>\n    <msubsup>\n     <mi>\n      x\n     </mi>\n     <mn>\n      1\n     </mn>\n     <mn>\n      2\n     </mn>\n    </msubsup>\n   </mrow>\n  </mfrac>\n </mrow>\n</math>",
                        "choiceId": "B",
                        "is_answer": false,
                        "explanation": ""
                    },
                    {
                        "text": "<math>\n <mrow>\n  <mfrac>\n   <mrow>\n    <msub>\n     <mi>\n      x\n     </mi>\n     <mn>\n      1\n     </mn>\n    </msub>\n   </mrow>\n   <mrow>\n    <msub>\n     <mi>\n      x\n     </mi>\n     <mn>\n      2\n     </mn>\n    </msub>\n   </mrow>\n  </mfrac>\n </mrow>\n</math>",
                        "choiceId": "C",
                        "is_answer": true,
                        "explanation": ""
                    },
                    {
                        "text": "<math>\n <mrow>\n  <mfrac>\n   <mrow>\n    <msub>\n     <mi>\n      x\n     </mi>\n     <mn>\n      2\n     </mn>\n    </msub>\n   </mrow>\n   <mrow>\n    <msub>\n     <mi>\n      x\n     </mi>\n     <mn>\n      1\n     </mn>\n    </msub>\n   </mrow>\n  </mfrac>\n </mrow>\n</math>",
                        "choiceId": "D",
                        "is_answer": false,
                        "explanation": ""
                    }
                ],
                "solution": "<img width=\"218\" height=\"188\" id=\"Picture 133\" src=\"https://d3vo8rtp78h2dc.cloudfront.net/lcmsnode/Image/1614875739680/JM20Phyimage170.png\">\n<br> Net field along AB at O must be zero.\n<br> E<sub>2</sub> cosα = E<sub>1</sub> sinα\n<br> \n<math>\n <mrow>\n  <mfrac>\n   <mrow>\n    <mi>\n     k\n    </mi>\n    <msub>\n     <mi>\n      Q\n     </mi>\n     <mn>\n      2\n     </mn>\n    </msub>\n   </mrow>\n   <mrow>\n    <msubsup>\n     <mi>\n      x\n     </mi>\n     <mn>\n      2\n     </mn>\n     <mn>\n      2\n     </mn>\n    </msubsup>\n   </mrow>\n  </mfrac>\n  <mo>\n   ⋅\n  </mo>\n  <mfrac>\n   <mrow>\n    <msub>\n     <mi>\n      x\n     </mi>\n     <mn>\n      2\n     </mn>\n    </msub>\n   </mrow>\n   <mrow>\n    <mi>\n     A\n    </mi>\n    <mi>\n     B\n    </mi>\n   </mrow>\n  </mfrac>\n  <mo>\n   =\n  </mo>\n  <mfrac>\n   <mrow>\n    <mi>\n     k\n    </mi>\n    <msub>\n     <mi>\n      Q\n     </mi>\n     <mn>\n      1\n     </mn>\n    </msub>\n   </mrow>\n   <mrow>\n    <msubsup>\n     <mi>\n      x\n     </mi>\n     <mn>\n      1\n     </mn>\n     <mn>\n      2\n     </mn>\n    </msubsup>\n   </mrow>\n  </mfrac>\n  <mo>\n   ⋅\n  </mo>\n  <mfrac>\n   <mrow>\n    <msub>\n     <mi>\n      x\n     </mi>\n     <mn>\n      1\n     </mn>\n    </msub>\n   </mrow>\n   <mrow>\n    <mi>\n     A\n    </mi>\n    <mi>\n     B\n    </mi>\n   </mrow>\n  </mfrac>\n </mrow>\n</math>\n<br> \n<math>\n <mrow>\n  <mfrac>\n   <mrow>\n    <msub>\n     <mi>\n      Q\n     </mi>\n     <mn>\n      1\n     </mn>\n    </msub>\n   </mrow>\n   <mrow>\n    <msub>\n     <mi>\n      Q\n     </mi>\n     <mn>\n      2\n     </mn>\n    </msub>\n   </mrow>\n  </mfrac>\n  <mo>\n   =\n  </mo>\n  <mfrac>\n   <mrow>\n    <msub>\n     <mi>\n      x\n     </mi>\n     <mn>\n      1\n     </mn>\n    </msub>\n   </mrow>\n   <mrow>\n    <msub>\n     <mi>\n      x\n     </mi>\n     <mn>\n      2\n     </mn>\n    </msub>\n   </mrow>\n  </mfrac>\n </mrow>\n</math>",
                "underlying_concept": "Electric field due to multiple charges",
                "new_possible_concepts": "Net field along AB at O must be zero.",
                "type": "SCMCQ",
                "sub_type": null,
                "difficulty": "E",
                "year": [
                    2020
                ],
                "similar_question": [],
                "answer": null,
                "list1": null,
                "list2": null,
                "topic_id": null
            },
            {
                "text": "<p>Two identical electric point dipoles have dipole moments&nbsp;\n <math xmlns=\"http://www.w3.org/1998/Math/MathML\">\n  <msub>\n   <mover>\n    <mi>\n     p\n    </mi>\n    <mo>\n     →\n    </mo>\n   </mover>\n   <mn>\n    1\n   </mn>\n  </msub><mo>\n   =\n  </mo><mi>\n   p\n  </mi><mover>\n   <mi>\n    i\n   </mi>\n   <mo>\n    ^\n   </mo>\n  </mover><mtext>\n    \n  </mtext><mtext>\n    \n  </mtext><mi>\n   and\n  </mi><mtext>\n    \n  </mtext><mtext>\n    \n  </mtext><msub>\n   <mover>\n    <mi>\n     p\n    </mi>\n    <mo>\n     →\n    </mo>\n   </mover>\n   <mn>\n    2\n   </mn>\n  </msub><mo>\n   =\n  </mo><mo>\n   –\n  </mo><mi>\n   p\n  </mi><mover>\n   <mi>\n    i\n   </mi>\n   <mo>\n    ^\n   </mo>\n  </mover>\n </math>&nbsp;and are held on the x axis at distance ‘a’ from each other. When released, they move along the x-axis with the direction of their dipole moments remaining unchanged. If the mass of each dipole is ‘m’, their speed when they are infinitely far apart is</p>",
                "choices": [
                    {
                        "text": "<math>\n <mrow>\n  <mfrac>\n   <mi>\n    p\n   </mi>\n   <mi>\n    a\n   </mi>\n  </mfrac>\n  <msqrt>\n   <mrow>\n    <mfrac>\n     <mn>\n      1\n     </mn>\n     <mrow>\n      <mn>\n       2\n      </mn>\n      <mi>\n       π\n      </mi>\n      <msub>\n       <mi>\n        ε\n       </mi>\n       <mn>\n        0\n       </mn>\n      </msub>\n      <mi>\n       m\n      </mi>\n      <mi>\n       a\n      </mi>\n     </mrow>\n    </mfrac>\n   </mrow>\n  </msqrt>\n </mrow>\n</math>",
                        "choiceId": "A",
                        "is_answer": true,
                        "explanation": ""
                    },
                    {
                        "text": "<math>\n <mrow>\n  <mfrac>\n   <mi>\n    p\n   </mi>\n   <mi>\n    a\n   </mi>\n  </mfrac>\n  <msqrt>\n   <mrow>\n    <mfrac>\n     <mn>\n      2\n     </mn>\n     <mrow>\n      <mi>\n       π\n      </mi>\n      <msub>\n       <mi>\n        ε\n       </mi>\n       <mn>\n        0\n       </mn>\n      </msub>\n      <mi>\n       m\n      </mi>\n      <mi>\n       a\n      </mi>\n     </mrow>\n    </mfrac>\n   </mrow>\n  </msqrt>\n </mrow>\n</math>",
                        "choiceId": "B",
                        "is_answer": false,
                        "explanation": ""
                    },
                    {
                        "text": "<math>\n <mrow>\n  <mfrac>\n   <mi>\n    p\n   </mi>\n   <mi>\n    a\n   </mi>\n  </mfrac>\n  <msqrt>\n   <mrow>\n    <mfrac>\n     <mn>\n      1\n     </mn>\n     <mrow>\n      <mi>\n       π\n      </mi>\n      <msub>\n       <mi>\n        ε\n       </mi>\n       <mn>\n        0\n       </mn>\n      </msub>\n      <mi>\n       m\n      </mi>\n      <mi>\n       a\n      </mi>\n     </mrow>\n    </mfrac>\n   </mrow>\n  </msqrt>\n </mrow>\n</math>",
                        "choiceId": "C",
                        "is_answer": false,
                        "explanation": ""
                    },
                    {
                        "text": "<math>\n <mrow>\n  <mfrac>\n   <mi>\n    p\n   </mi>\n   <mi>\n    a\n   </mi>\n  </mfrac>\n  <msqrt>\n   <mrow>\n    <mfrac>\n     <mn>\n      3\n     </mn>\n     <mrow>\n      <mn>\n       2\n      </mn>\n      <mi>\n       π\n      </mi>\n      <msub>\n       <mi>\n        ε\n       </mi>\n       <mn>\n        0\n       </mn>\n      </msub>\n      <mi>\n       m\n      </mi>\n      <mi>\n       a\n      </mi>\n     </mrow>\n    </mfrac>\n   </mrow>\n  </msqrt>\n </mrow>\n</math>",
                        "choiceId": "D",
                        "is_answer": false,
                        "explanation": ""
                    }
                ],
                "solution": "<p>\n <math>\n  <mover accent=\"true\">\n   <mi>\n    p\n   </mi>&nbsp;\n   <mo>\n    →\n   </mo>&nbsp;\n  </mover>\n </math>&nbsp; &nbsp; &nbsp; &nbsp; &nbsp;&nbsp;\n <math>\n  <mrow>\n   <mover accent=\"true\">\n    <mrow>\n     <mi>\n      p\n     </mi>&nbsp;\n     <mo>\n      •\n     </mo>&nbsp;\n    </mrow>\n    <mo stretchy=\"true\">\n     ←\n    </mo>&nbsp;\n   </mover>\n  </mrow>\n </math><br>\n <math>\n  <mrow>\n   <mi>\n    U\n   </mi>&nbsp;\n   <mo>\n    =\n   </mo>&nbsp;\n   <mo>\n    –\n   </mo>&nbsp;\n   <mover accent=\"true\">\n    <mi>\n     p\n    </mi>&nbsp;\n    <mo>\n     →\n    </mo>&nbsp;\n   </mover>\n   <mo>\n    ⋅\n   </mo>&nbsp;\n   <mover accent=\"true\">\n    <mi>\n     E\n    </mi>&nbsp;\n    <mo>\n     →\n    </mo>&nbsp;\n   </mover>\n  </mrow>\n </math><br>\n <math>\n  <mrow>\n   <mover accent=\"true\">\n    <mi>\n     E\n    </mi>&nbsp;\n    <mo>\n     →\n    </mo>&nbsp;\n   </mover>\n   <mo>\n    =\n   </mo>&nbsp;\n   <mfrac>\n    <mrow>\n     <mn>\n      2\n     </mn>&nbsp;\n     <mover accent=\"true\">\n      <mi>\n       p\n      </mi>&nbsp;\n      <mo>\n       →\n      </mo>&nbsp;\n     </mover>\n    </mrow>\n    <mrow>\n     <mn>\n      4\n     </mn>&nbsp;\n     <mi>\n      π\n     </mi>&nbsp;\n     <msub>\n      <mi>\n       ε\n      </mi>&nbsp;\n      <mn>\n       0\n      </mn>&nbsp;\n     </msub>\n     <mo>\n      ×\n     </mo>&nbsp;\n     <msup>\n      <mi>\n       a\n      </mi>&nbsp;\n      <mn>\n       3\n      </mn>&nbsp;\n     </msup>\n    </mrow>\n   </mfrac>\n  </mrow>\n </math><br>∴&nbsp;\n <math>\n  <mrow>\n   <mi>\n    Δ\n   </mi>&nbsp;\n   <msub>\n    <mi>\n     U\n    </mi>&nbsp;\n    <mrow>\n     <mi>\n      l\n     </mi>&nbsp;\n     <mi>\n      o\n     </mi>&nbsp;\n     <mi>\n      s\n     </mi>&nbsp;\n     <mi>\n      s\n     </mi>&nbsp;\n    </mrow>\n   </msub>\n   <mo>\n    =\n   </mo>&nbsp;\n   <mfrac>\n    <mrow>\n     <mn>\n      2\n     </mn>&nbsp;\n     <msup>\n      <mi>\n       p\n      </mi>&nbsp;\n      <mn>\n       2\n      </mn>&nbsp;\n     </msup>\n    </mrow>\n    <mrow>\n     <mn>\n      4\n     </mn>&nbsp;\n     <mi>\n      π\n     </mi>&nbsp;\n     <msub>\n      <mi>\n       ε\n      </mi>&nbsp;\n      <mn>\n       0\n      </mn>&nbsp;\n     </msub>\n     <msup>\n      <mi>\n       a\n      </mi>&nbsp;\n      <mn>\n       3\n      </mn>&nbsp;\n     </msup>\n    </mrow>\n   </mfrac>\n   <mo>\n    =\n   </mo>&nbsp;\n   <mn>\n    2\n   </mn>&nbsp;\n   <mo>\n    ×\n   </mo>&nbsp;\n   <mfrac>\n    <mn>\n     1\n    </mn>&nbsp;\n    <mn>\n     2\n    </mn>&nbsp;\n   </mfrac>\n   <mi>\n    m\n   </mi>&nbsp;\n   <msup>\n    <mi>\n     v\n    </mi>&nbsp;\n    <mn>\n     2\n    </mn>&nbsp;\n   </msup>\n  </mrow>\n </math><br>⇒&nbsp;\n <math>\n  <mrow>\n   <mi>\n    v\n   </mi>&nbsp;\n   <mo>\n    =\n   </mo>&nbsp;\n   <mfrac>\n    <mi>\n     p\n    </mi>&nbsp;\n    <mi>\n     a\n    </mi>&nbsp;\n   </mfrac>\n   <msqrt>\n    <mrow>\n     <mfrac>\n      <mn>\n       1\n      </mn>&nbsp;\n      <mrow>\n       <mn>\n        2\n       </mn>&nbsp;\n       <mi>\n        π\n       </mi>&nbsp;\n       <msub>\n        <mi>\n         ε\n        </mi>&nbsp;\n        <mn>\n         0\n        </mn>&nbsp;\n       </msub>\n       <mi>\n        m\n       </mi>&nbsp;\n       <mi>\n        a\n       </mi>&nbsp;\n      </mrow>\n     </mfrac>\n    </mrow>\n   </msqrt>\n  </mrow>\n </math></p>",
                "underlying_concept": "Electric dipoles",
                "new_possible_concepts": "|Change in energy| = U<sub>i </sub>– U<sub>f</sub>\n<br> Decrease in PE is equal to the Increase in KE",
                "type": "SCMCQ",
                "sub_type": null,
                "difficulty": "M",
                "year": [
                    2020
                ],
                "similar_question": [],
                "answer": null,
                "list1": null,
                "list2": null,
                "topic_id": null
            },
            {
                "text": "<p>A charged particle going around in a circle can be considered to be a current loop. A particle of mass m carrying charge q is moving in a plane with speed v under the influence of magnetic field&nbsp;\n <math xmlns=\"http://www.w3.org/1998/Math/MathML\">\n  <mover>\n   <mi>\n    B\n   </mi>\n   <mo>\n    →\n   </mo>\n  </mover>\n </math>. The magnetic moment of this moving particle :</p>",
                "choices": [
                    {
                        "text": "<math>\n <mrow>\n  <mo>\n   –\n  </mo>\n  <mfrac>\n   <mrow>\n    <mi>\n     m\n    </mi>\n    <msup>\n     <mi>\n      v\n     </mi>\n     <mn>\n      2\n     </mn>\n    </msup>\n    <mover accent=\"true\">\n     <mi>\n      B\n     </mi>\n     <mo>\n      →\n     </mo>\n    </mover>\n   </mrow>\n   <mrow>\n    <mn>\n     2\n    </mn>\n    <mtext>\n      \n    </mtext>\n    <mtext>\n      \n    </mtext>\n    <msup>\n     <mi>\n      B\n     </mi>\n     <mn>\n      2\n     </mn>\n    </msup>\n   </mrow>\n  </mfrac>\n </mrow>\n</math>",
                        "choiceId": "A",
                        "is_answer": true,
                        "explanation": ""
                    },
                    {
                        "text": "<math>\n <mrow>\n  <mfrac>\n   <mrow>\n    <mi>\n     m\n    </mi>\n    <msup>\n     <mi>\n      v\n     </mi>\n     <mn>\n      2\n     </mn>\n    </msup>\n    <mover accent=\"true\">\n     <mi>\n      B\n     </mi>\n     <mo>\n      →\n     </mo>\n    </mover>\n   </mrow>\n   <mrow>\n    <mn>\n     2\n    </mn>\n    <mtext>\n      \n    </mtext>\n    <mtext>\n      \n    </mtext>\n    <msup>\n     <mi>\n      B\n     </mi>\n     <mn>\n      2\n     </mn>\n    </msup>\n   </mrow>\n  </mfrac>\n </mrow>\n</math>",
                        "choiceId": "B",
                        "is_answer": false,
                        "explanation": ""
                    },
                    {
                        "text": "<math>\n <mrow>\n  <mo>\n   –\n  </mo>\n  <mfrac>\n   <mrow>\n    <mi>\n     m\n    </mi>\n    <msup>\n     <mi>\n      v\n     </mi>\n     <mn>\n      2\n     </mn>\n    </msup>\n    <mover accent=\"true\">\n     <mi>\n      B\n     </mi>\n     <mo>\n      →\n     </mo>\n    </mover>\n   </mrow>\n   <mrow>\n    <mn>\n     2\n    </mn>\n    <mtext>\n      \n    </mtext>\n    <mtext>\n      \n    </mtext>\n    <mi>\n     π\n    </mi>\n    <msup>\n     <mi>\n      B\n     </mi>\n     <mn>\n      2\n     </mn>\n    </msup>\n   </mrow>\n  </mfrac>\n </mrow>\n</math>",
                        "choiceId": "C",
                        "is_answer": false,
                        "explanation": ""
                    },
                    {
                        "text": "<math>\n <mrow>\n  <mo>\n   –\n  </mo>\n  <mfrac>\n   <mrow>\n    <mi>\n     m\n    </mi>\n    <msup>\n     <mi>\n      v\n     </mi>\n     <mn>\n      2\n     </mn>\n    </msup>\n    <mover accent=\"true\">\n     <mi>\n      B\n     </mi>\n     <mo>\n      →\n     </mo>\n    </mover>\n   </mrow>\n   <mrow>\n    <msup>\n     <mi>\n      B\n     </mi>\n     <mn>\n      2\n     </mn>\n    </msup>\n   </mrow>\n  </mfrac>\n </mrow>\n</math>",
                        "choiceId": "D",
                        "is_answer": false,
                        "explanation": ""
                    }   
                ],
                "solution": "<math>\n <mrow>\n  <mover accent=\"true\">\n   <mi>\n    M\n   </mi>\n   <mo>\n    →\n   </mo>\n  </mover>\n  <mo>\n   =\n  </mo>\n  <mfrac>\n   <mn>\n    1\n   </mn>\n   <mn>\n    2\n   </mn>\n  </mfrac>\n  <mi>\n   q\n  </mi>\n  <mi>\n   v\n  </mi>\n  <mi>\n   R\n  </mi>\n  <mtext>\n    \n  </mtext>\n  <mo stretchy=\"false\">\n   (\n  </mo>\n  <mo>\n   –\n  </mo>\n  <mover accent=\"true\">\n   <mi>\n    B\n   </mi>\n   <mo>\n    ^\n   </mo>\n  </mover>\n  <mo stretchy=\"false\">\n   )\n  </mo>\n </mrow>\n</math>\n<br> \n<img width=\"140\" height=\"71\" id=\"Picture 167\" src=\"https://d3vo8rtp78h2dc.cloudfront.net/lcmsnode/Image/1614875739684/JM20Phyimage193.png\">\n<br> \n<math>\n <mrow>\n  <mo>\n   =\n  </mo>\n  <mfrac>\n   <mrow>\n    <mi>\n     q\n    </mi>\n    <mi>\n     v\n    </mi>\n   </mrow>\n   <mn>\n    2\n   </mn>\n  </mfrac>\n  <mtext>\n    \n  </mtext>\n  <mfenced>\n   <mrow>\n    <mfrac>\n     <mrow>\n      <mi>\n       m\n      </mi>\n      <mi>\n       v\n      </mi>\n     </mrow>\n     <mrow>\n      <mi>\n       q\n      </mi>\n      <mi>\n       B\n      </mi>\n     </mrow>\n    </mfrac>\n   </mrow>\n  </mfenced>\n  <mtext>\n    \n  </mtext>\n  <mfenced>\n   <mrow>\n    <mfrac>\n     <mrow>\n      <mo>\n       –\n      </mo>\n      <mover accent=\"true\">\n       <mi>\n        B\n       </mi>\n       <mo>\n        →\n       </mo>\n      </mover>\n     </mrow>\n     <mi>\n      B\n     </mi>\n    </mfrac>\n   </mrow>\n  </mfenced>\n </mrow>\n</math>\n<br> \n<math>\n <mrow>\n  <mo>\n   =\n  </mo>\n  <mo>\n   –\n  </mo>\n  <mfrac>\n   <mrow>\n    <mi>\n     m\n    </mi>\n    <msup>\n     <mi>\n      v\n     </mi>\n     <mn>\n      2\n     </mn>\n    </msup>\n   </mrow>\n   <mrow>\n    <mn>\n     2\n    </mn>\n    <msup>\n     <mi>\n      B\n     </mi>\n     <mn>\n      2\n     </mn>\n    </msup>\n   </mrow>\n  </mfrac>\n  <mtext>\n    \n  </mtext>\n  <mover accent=\"true\">\n   <mi>\n    B\n   </mi>\n   <mo>\n    →\n   </mo>\n  </mover>\n </mrow>\n</math>"
            }
        ]
    }
}